README.md
setup.py
mybatis_mapper2sql/__init__.py
mybatis_mapper2sql/convert.py
mybatis_mapper2sql/generate.py
mybatis_mapper2sql/params.py
mybatis_mapper2sql.egg-info/PKG-INFO
mybatis_mapper2sql.egg-info/SOURCES.txt
mybatis_mapper2sql.egg-info/dependency_links.txt
mybatis_mapper2sql.egg-info/not-zip-safe
mybatis_mapper2sql.egg-info/requires.txt
mybatis_mapper2sql.egg-info/top_level.txt
tests/__init__.py
tests/test.py