Metadata-Version: 2.1
Name: mybatis-mapper2sql
Version: 0.1.7
Summary: Generate SQL Statements from the MyBatis3 Mapper XML file
Home-page: http://github.com/hhyo/mybatis-mapper2sql
Author: hhyo
Author-email: rtttte@qq.com
License: Apache 2.0
Keywords: mybatis mapper2sql mybatis-mapper2sql
Platform: UNKNOWN
Classifier: Development Status :: 3 - Alpha
Classifier: Intended Audience :: Developers
Classifier: License :: OSI Approved :: Apache Software License
Classifier: Operating System :: OS Independent
Classifier: Programming Language :: Python :: 3
Classifier: Programming Language :: Python :: 3.4
Classifier: Programming Language :: Python :: 3.5
Classifier: Programming Language :: Python :: 3.6
Classifier: Programming Language :: Python :: 3.7
